{
  "product": "知更",
  "parent_product": "百灵",
  "version": "auth-workspace-expanded-pack-3",
  "generated_at": "2026-06-14T00:24:27",
  "industry_input_generated_at": "2026-06-15T07:00:08",
  "source_item_count": 289,
  "space_count": 6,
  "roles": [
    {
      "id": "public",
      "name": "公开用户",
      "status": "可直接使用",
      "description": "浏览百灵公开信息流、行业空间、原文链接和基础搜索筛选。",
      "features": [
        "公开信息流",
        "行业空间浏览",
        "原文跳转",
        "基础筛选"
      ],
      "limits": [
        "无个人订阅",
        "无客户简报",
        "无深度摘要"
      ]
    },
    {
      "id": "applicant",
      "name": "认证申请中",
      "status": "提交资料后",
      "description": "选择行业方向，提交身份或职业材料，进入知更专业层审核。",
      "features": [
        "行业偏好",
        "试用晨报",
        "收藏夹",
        "申请进度"
      ],
      "limits": [
        "专业报告导出受限",
        "客户空间不可用"
      ]
    },
    {
      "id": "verified",
      "name": "知更认证顾问",
      "status": "审核通过",
      "description": "开启顾问工作台，用于客户晨报、专题追踪、PPT 素材卡和项目资料整理。",
      "features": [
        "客户晨报",
        "PPT 素材卡",
        "影响矩阵",
        "专题追踪",
        "行业订阅"
      ],
      "limits": [
        "需遵守来源版权和引用规范",
        "公众号等授权源需单独开通"
      ]
    }
  ],
  "application_steps": [
    {
      "name": "选择身份",
      "detail": "个人用户、企业经营者、咨询顾问、行业研究员。"
    },
    {
      "name": "选择行业",
      "detail": "从管理咨询、制造业、能源基建、财政金融、区域招商等空间中选择。"
    },
    {
      "name": "提交证明",
      "detail": "可用公司邮箱、名片、项目经历或机构证明。"
    },
    {
      "name": "开通知更",
      "detail": "审核后获得专业工具、订阅和工作台能力。"
    }
  ],
  "pro_tools": [
    {
      "id": "morning_brief",
      "name": "客户晨报",
      "stage": "认证后开放",
      "description": "把行业空间里的高分线索整理成客户可读的晨报提纲。",
      "inputs": [
        "行业空间",
        "客户行业",
        "关注关键词"
      ],
      "outputs": [
        "今日重点",
        "顾问解读",
        "建议动作"
      ]
    },
    {
      "id": "ppt_cards",
      "name": "PPT 素材卡",
      "stage": "认证后开放",
      "description": "把政策、数据、公告转成可进入咨询汇报的素材卡。",
      "inputs": [
        "原文链接",
        "指标或政策标题",
        "项目主题"
      ],
      "outputs": [
        "事实卡",
        "影响判断",
        "引用链接"
      ]
    },
    {
      "id": "impact_matrix",
      "name": "影响矩阵",
      "stage": "认证后开放",
      "description": "按客户、行业、区域、时间维度评估政策和数据影响。",
      "inputs": [
        "政策条目",
        "客户类型",
        "区域"
      ],
      "outputs": [
        "机会",
        "风险",
        "待确认问题"
      ]
    },
    {
      "id": "topic_tracker",
      "name": "专题追踪",
      "stage": "认证后开放",
      "description": "围绕十五五、外资、民营经济、价格、PMI 等主题持续追踪。",
      "inputs": [
        "主题关键词",
        "信源范围",
        "更新频率"
      ],
      "outputs": [
        "变化记录",
        "关键节点",
        "提醒"
      ]
    }
  ],
  "spaces": [
    {
      "id": "consulting",
      "name": "管理咨询",
      "audience": "咨询顾问 / 项目经理",
      "item_count": 153,
      "brief": "今日重点集中在国家政策，建议关注政策窗口、客户简报、项目背景。",
      "recommended_tools": [
        "客户晨报",
        "PPT 素材卡",
        "影响矩阵"
      ],
      "top_titles": [
        "国办关于加强监管防范风险促进私募投资基金高质量发展的指导意见",
        "国务院关于印发《现代化应急体系建设“十五五”规划》的通知",
        "关于印发《生态保护修复领域中央预算内投资专项管理办法》的通知(发改农经〔2026〕713号)"
      ]
    },
    {
      "id": "manufacturing",
      "name": "制造业",
      "audience": "制造企业 / 产业园区",
      "item_count": 18,
      "brief": "今日重点集中在宏观数据，建议关注景气变化、成本压力、产业政策。",
      "recommended_tools": [
        "产业链追踪",
        "竞品动向",
        "成本预警"
      ],
      "top_titles": [
        "2026年5月份工业生产者出厂价格同比上涨3.9% 环比上涨0.5%",
        "2026年5月份居民消费价格同比上涨1.2%",
        "国内成品油价格调整"
      ]
    },
    {
      "id": "energy_infra",
      "name": "能源与基础设施",
      "audience": "能源、公用事业、基建客户",
      "item_count": 21,
      "brief": "今日重点集中在国家政策，建议关注项目约束、监管变化、基础设施机会。",
      "recommended_tools": [
        "项目机会库",
        "区域政策比对",
        "风险条款摘要"
      ],
      "top_titles": [
        "国务院关于印发《现代化应急体系建设“十五五”规划》的通知",
        "关于印发《非化石能源电力消费核算指南(试行)》的通知(发改能源〔2026〕622号)",
        "《电力重大事故隐患判定标准及治理监督管理规定》 2026年第41号令"
      ]
    },
    {
      "id": "finance",
      "name": "财政金融",
      "audience": "投融资、财务、金融机构",
      "item_count": 55,
      "brief": "今日重点集中在财政金融，建议关注资金环境、融资窗口、监管倾向。",
      "recommended_tools": [
        "融资环境雷达",
        "政策原文摘要",
        "机构观点汇总"
      ],
      "top_titles": [
        "财政部第二次续发行2026年记账式附息（八期）国债",
        "财政部发行2026年记账式附息（十二期）国债",
        "中国人民银行与国际清算银行共同主办“应对全球金融不确定性——金融市场发展、投资策略与国际货币体系”高级别会议"
      ]
    },
    {
      "id": "regional",
      "name": "区域招商",
      "audience": "地方政府 / 园区 / 招商团队",
      "item_count": 40,
      "brief": "今日重点集中在国家政策，建议关注招商方向、资金支持、产业目录。",
      "recommended_tools": [
        "招商话术",
        "政策对标",
        "项目线索"
      ],
      "top_titles": [
        "关于印发《生态保护修复领域中央预算内投资专项管理办法》的通知(发改农经〔2026〕713号)",
        "《中央预算内投资补助和贴息项目管理办法》 2025年第38号令",
        "《鼓励外商投资产业目录(2025年版)》 2025年第37号令"
      ]
    },
    {
      "id": "macro_ops",
      "name": "宏观经营",
      "audience": "企业主 / 经营管理者",
      "item_count": 15,
      "brief": "今日重点集中在宏观数据，建议关注需求变化、价格趋势、经营压力。",
      "recommended_tools": [
        "经营晨报",
        "指标看板",
        "管理层简报"
      ],
      "top_titles": [
        "2026年5月份居民消费价格同比上涨1.2%",
        "2026年5月中国采购经理指数运行情况",
        "国内成品油价格调整"
      ]
    }
  ],
  "category_distribution": {
    "国家政策": 34,
    "宏观数据": 12,
    "地方政策": 2,
    "财政金融": 11,
    "外贸外资": 1
  },
  "input_generated_at": "2026-06-15T07:00:08"
}